main_system.v
// PIR Sensor Module
module pir(
    input wire clk,
    input wire reset,
    input wire motion_detected_in,
    input wire push_button,
    output reg motion_detected,
    output reg [1:0] state
);
    // State encoding
    localparam OFF = 2'b00,
               IDLE = 2'b01,
               MOTION_DETECTED = 2'b10,
               INTERRUPT = 2'b11;

    reg [5:0] countdown;

    always @(posedge clk or posedge reset) begin
        if (reset) begin
            state <= OFF;
            motion_detected <= 1'b0;
            countdown <= 6'd0;
        end else begin
            case (state)
                OFF: begin
                    if (!reset) state <= IDLE;
                end

                IDLE: begin
                    if (motion_detected_in) begin
                        state <= MOTION_DETECTED;
                        motion_detected <= 1'b1;
                    end
                end

                MOTION_DETECTED: begin
                    if (push_button) begin
                        state <= INTERRUPT;
                        motion_detected <= 1'b0;
                        countdown <= 6'd60; // 1-minute countdown
                    end
                end

                INTERRUPT: begin
                    if (countdown > 0)
                        countdown <= countdown - 1;
                    else
                        state <= IDLE;
                end
            endcase
        end
    end
endmodule

// Buzzer Module
module buzzer(
    input wire motion_detected,
    output reg buzzer_signal
);
    always @(*) begin
        buzzer_signal = motion_detected;
    end
endmodule

// LED RGB Module
module led_rgb(
    input wire [1:0] state,
    output reg [2:0] led_color // RGB encoding: Green = 3'b010, Red = 3'b100, Blue = 3'b001
);
    always @(*) begin
        case (state)
            2'b00: led_color = 3'b000; // OFF
            2'b01: led_color = 3'b010; // Green (IDLE)
            2'b10: led_color = 3'b100; // Red (MOTION_DETECTED)
            2'b11: led_color = 3'b001; // Blue (INTERRUPT)
            default: led_color = 3'b000;
        endcase
    end
endmodule

// RTC Module
module rtc(
    input wire clk,
    input wire reset,
    output reg [31:0] time_data, // Placeholder for time representation
    output reg [5:0] countdown
);
    always @(posedge clk or posedge reset) begin
        if (reset) begin
            time_data <= 32'd0;
            countdown <= 6'd0;
        end else begin
            time_data <= time_data + 1; // Increment time for simulation
        end
    end
endmodule

// LCD Module
module lcd(
    input wire [1:0] state,
    input wire [31:0] time_data,
    input wire [5:0] countdown,
    output reg [127:0] display_text // Placeholder for LCD text
);
    always @(*) begin
        case (state)
            2'b00: display_text = "System OFF";
            2'b01: display_text = {"Sensor aktif: ", time_data};
            2'b10: display_text = "Gerakan Terdeteksi";
            2'b11: display_text = {"Countdown: ", countdown};
            default: display_text = "Unknown State";
        endcase
    end
endmodule

// Top-level Module
module main_system(
    input wire clk,
    input wire reset,
    input wire motion_detected_in,
    input wire push_button,
    output wire buzzer_signal,
    output wire [2:0] led_color,
    output wire [127:0] display_text
);
    wire [1:0] state;
    wire motion_detected;
    wire [31:0] time_data;
    wire [5:0] countdown;

    pir pir_inst(
        .clk(clk),
        .reset(reset),
        .motion_detected_in(motion_detected_in),
        .push_button(push_button),
        .motion_detected(motion_detected),
        .state(state)
    );

    buzzer buzzer_inst(
        .motion_detected(motion_detected),
        .buzzer_signal(buzzer_signal)
    );

    led_rgb led_rgb_inst(
        .state(state),
        .led_color(led_color)
    );

    rtc rtc_inst(
        .clk(clk),
        .reset(reset),
        .time_data(time_data),
        .countdown(countdown)
    );

    lcd lcd_inst(
        .state(state),
        .time_data(time_data),
        .countdown(countdown),
        .display_text(display_text)
    );
endmodule

main_system_tb.v
// Testbench for main_system module
`timescale 1ns/1ps

module main_system_tb;
    // Testbench signals
    reg clk;
    reg reset;
    reg motion_detected_in;
    reg push_button;
    wire buzzer_signal;
    wire [2:0] led_color;
    wire [127:0] display_text;

    // Instantiate the main_system module
    main_system uut (
        .clk(clk),
        .reset(reset),
        .motion_detected_in(motion_detected_in),
        .push_button(push_button),
        .buzzer_signal(buzzer_signal),
        .led_color(led_color),
        .display_text(display_text)
    );

    // Clock generation
    always #1 clk = ~clk; // 100 MHz clock

    // Test sequence
    initial begin
        // Initialize signals
        clk = 0;
        reset = 1;
        motion_detected_in = 0;
        push_button = 0;

        // Reset system
        #10 reset = 0;

        // Test case 1: System transitions to IDLE
        #10 motion_detected_in = 0; // No motion yet

        // Test case 2: Motion detected
        #20 motion_detected_in = 1; // Simulate motion detection
        #10 motion_detected_in = 0; // Stop motion signal

        // Test case 3: Interrupt via push button
        #30 push_button = 1; // Simulate push button press
        #10 push_button = 0; // Release push button

        // Wait for countdown to complete
        #600;

        // Test case 4: Return to IDLE
        // After countdown, the system should return to IDLE

        // End simulation
        #50 $stop;
    end

    // Monitor output
    initial begin
        $dumpfile("testbench.vcd");
        $dumpvars(0, main_system_tb);
        $monitor("Time: %0d | Reset: %b | Motion: %b | Button: %b | State: %h | Buzzer: %b | LED: %b | Display: %s",
                 $time, reset, motion_detected_in, push_button, uut.pir_inst.state, buzzer_signal, led_color, display_text);
    end
endmodule

testbench.vcd
$date
	Sun Jan 05 22:23:16 2025
$end
$version
	Icarus Verilog
$end
$timescale
	1ps
$end
$scope module main_system_tb $end
$var wire 3 ! led_color [2:0] $end
$var wire 128 " display_text [127:0] $end
$var wire 1 # buzzer_signal $end
$var reg 1 $ clk $end
$var reg 1 % motion_detected_in $end
$var reg 1 & push_button $end
$var reg 1 ' reset $end
$scope module uut $end
$var wire 1 $ clk $end
$var wire 1 % motion_detected_in $end
$var wire 1 & push_button $end
$var wire 1 ' reset $end
$var wire 32 ( time_data [31:0] $end
$var wire 2 ) state [1:0] $end
$var wire 1 * motion_detected $end
$var wire 3 + led_color [2:0] $end
$var wire 128 , display_text [127:0] $end
$var wire 6 - countdown [5:0] $end
$var wire 1 # buzzer_signal $end
$scope module buzzer_inst $end
$var wire 1 * motion_detected $end
$var reg 1 # buzzer_signal $end
$upscope $end
$scope module lcd_inst $end
$var wire 32 . time_data [31:0] $end
$var wire 2 / state [1:0] $end
$var wire 6 0 countdown [5:0] $end
$var reg 128 1 display_text [127:0] $end
$upscope $end
$scope module led_rgb_inst $end
$var wire 2 2 state [1:0] $end
$var reg 3 3 led_color [2:0] $end
$upscope $end
$scope module pir_inst $end
$var wire 1 $ clk $end
$var wire 1 % motion_detected_in $end
$var wire 1 & push_button $end
$var wire 1 ' reset $end
$var parameter 2 4 IDLE $end
$var parameter 2 5 INTERRUPT $end
$var parameter 2 6 MOTION_DETECTED $end
$var parameter 2 7 OFF $end
$var reg 6 8 countdown [5:0] $end
$var reg 1 * motion_detected $end
$var reg 2 9 state [1:0] $end
$upscope $end
$scope module rtc_inst $end
$var wire 1 $ clk $end
$var wire 1 ' reset $end
$var reg 6 : countdown [5:0] $end
$var reg 32 ; time_data [31:0] $end
$upscope $end
$upscope $end
$upscope $end
$enddefinitions $end
$comment Show the parameter values. $end
$dumpall
b0 7
b10 6
b11 5
b1 4
$end
#0
$dumpvars
b0 ;
b0 :
b0 9
b0 8
b0 3
b0 2
b1010011011110010111001101110100011001010110110100100000010011110100011001000110 1
b0 0
b0 /
b0 .
b0 -
b1010011011110010111001101110100011001010110110100100000010011110100011001000110 ,
b0 +
0*
b0 )
b0 (
1'
0&
0%
0$
0#
b1010011011110010111001101110100011001010110110100100000010011110100011001000110 "
b0 !
$end
#1000
1$
#2000
0$
#3000
1$
#4000
0$
#5000
1$
#6000
0$
#7000
1$
#8000
0$
#9000
1$
#10000
0$
0'
#11000
b10 !
b10 +
b10 3
b1101110011100110110111101110010001000000110000101101011011101000110100101100110001110100010000000000000000000000000000000000001 "
b1101110011100110110111101110010001000000110000101101011011101000110100101100110001110100010000000000000000000000000000000000001 ,
b1101110011100110110111101110010001000000110000101101011011101000110100101100110001110100010000000000000000000000000000000000001 1
b1 )
b1 /
b1 2
b1 9
b1 (
b1 .
b1 ;
1$
#12000
0$
#13000
b1101110011100110110111101110010001000000110000101101011011101000110100101100110001110100010000000000000000000000000000000000010 "
b1101110011100110110111101110010001000000110000101101011011101000110100101100110001110100010000000000000000000000000000000000010 ,
b1101110011100110110111101110010001000000110000101101011011101000110100101100110001110100010000000000000000000000000000000000010 1
b10 (
b10 .
b10 ;
1$
#14000
0$
#15000
b1101110011100110110111101110010001000000110000101101011011101000110100101100110001110100010000000000000000000000000000000000011 "
b1101110011100110110111101110010001000000110000101101011011101000110100101100110001110100010000000000000000000000000000000000011 ,
b1101110011100110110111101110010001000000110000101101011011101000110100101100110001110100010000000000000000000000000000000000011 1
b11 (
b11 .
b11 ;
1$
#16000
0$
#17000
b1101110011100110110111101110010001000000110000101101011011101000110100101100110001110100010000000000000000000000000000000000100 "
b1101110011100110110111101110010001000000110000101101011011101000110100101100110001110100010000000000000000000000000000000000100 ,
b1101110011100110110111101110010001000000110000101101011011101000110100101100110001110100010000000000000000000000000000000000100 1
b100 (
b100 .
b100 ;
1$
#18000
0$
#19000
b1101110011100110110111101110010001000000110000101101011011101000110100101100110001110100010000000000000000000000000000000000101 "
b1101110011100110110111101110010001000000110000101101011011101000110100101100110001110100010000000000000000000000000000000000101 ,
b1101110011100110110111101110010001000000110000101101011011101000110100101100110001110100010000000000000000000000000000000000101 1
b101 (
b101 .
b101 ;
1$
#20000
0$
#21000
b1101110011100110110111101110010001000000110000101101011011101000110100101100110001110100010000000000000000000000000000000000110 "
b1101110011100110110111101110010001000000110000101101011011101000110100101100110001110100010000000000000000000000000000000000110 ,
b1101110011100110110111101110010001000000110000101101011011101000110100101100110001110100010000000000000000000000000000000000110 1
b110 (
b110 .
b110 ;
1$
#22000
0$
#23000
b1101110011100110110111101110010001000000110000101101011011101000110100101100110001110100010000000000000000000000000000000000111 "
b1101110011100110110111101110010001000000110000101101011011101000110100101100110001110100010000000000000000000000000000000000111 ,
b1101110011100110110111101110010001000000110000101101011011101000110100101100110001110100010000000000000000000000000000000000111 1
b111 (
b111 .
b111 ;
1$
#24000
0$
#25000
b1101110011100110110111101110010001000000110000101101011011101000110100101100110001110100010000000000000000000000000000000001000 "
b1101110011100110110111101110010001000000110000101101011011101000110100101100110001110100010000000000000000000000000000000001000 ,
b1101110011100110110111101110010001000000110000101101011011101000110100101100110001110100010000000000000000000000000000000001000 1
b1000 (
b1000 .
b1000 ;
1$
#26000
0$
#27000
b1101110011100110110111101110010001000000110000101101011011101000110100101100110001110100010000000000000000000000000000000001001 "
b1101110011100110110111101110010001000000110000101101011011101000110100101100110001110100010000000000000000000000000000000001001 ,
b1101110011100110110111101110010001000000110000101101011011101000110100101100110001110100010000000000000000000000000000000001001 1
b1001 (
b1001 .
b1001 ;
1$
#28000
0$
#29000
b1101110011100110110111101110010001000000110000101101011011101000110100101100110001110100010000000000000000000000000000000001010 "
b1101110011100110110111101110010001000000110000101101011011101000110100101100110001110100010000000000000000000000000000000001010 ,
b1101110011100110110111101110010001000000110000101101011011101000110100101100110001110100010000000000000000000000000000000001010 1
b1010 (
b1010 .
b1010 ;
1$
#30000
0$
#31000
b1101110011100110110111101110010001000000110000101101011011101000110100101100110001110100010000000000000000000000000000000001011 "
b1101110011100110110111101110010001000000110000101101011011101000110100101100110001110100010000000000000000000000000000000001011 ,
b1101110011100110110111101110010001000000110000101101011011101000110100101100110001110100010000000000000000000000000000000001011 1
b1011 (
b1011 .
b1011 ;
1$
#32000
0$
#33000
b1101110011100110110111101110010001000000110000101101011011101000110100101100110001110100010000000000000000000000000000000001100 "
b1101110011100110110111101110010001000000110000101101011011101000110100101100110001110100010000000000000000000000000000000001100 ,
b1101110011100110110111101110010001000000110000101101011011101000110100101100110001110100010000000000000000000000000000000001100 1
b1100 (
b1100 .
b1100 ;
1$
#34000
0$
#35000
b1101110011100110110111101110010001000000110000101101011011101000110100101100110001110100010000000000000000000000000000000001101 "
b1101110011100110110111101110010001000000110000101101011011101000110100101100110001110100010000000000000000000000000000000001101 ,
b1101110011100110110111101110010001000000110000101101011011101000110100101100110001110100010000000000000000000000000000000001101 1
b1101 (
b1101 .
b1101 ;
1$
#36000
0$
#37000
b1101110011100110110111101110010001000000110000101101011011101000110100101100110001110100010000000000000000000000000000000001110 "
b1101110011100110110111101110010001000000110000101101011011101000110100101100110001110100010000000000000000000000000000000001110 ,
b1101110011100110110111101110010001000000110000101101011011101000110100101100110001110100010000000000000000000000000000000001110 1
b1110 (
b1110 .
b1110 ;
1$
#38000
0$
#39000
b1101110011100110110111101110010001000000110000101101011011101000110100101100110001110100010000000000000000000000000000000001111 "
b1101110011100110110111101110010001000000110000101101011011101000110100101100110001110100010000000000000000000000000000000001111 ,
b1101110011100110110111101110010001000000110000101101011011101000110100101100110001110100010000000000000000000000000000000001111 1
b1111 (
b1111 .
b1111 ;
1$
#40000
0$
1%
#41000
1#
b1110010011000010110101101100001011011100010000001010100011001010111001001100100011001010111010001100101011010110111001101101001 "
b1110010011000010110101101100001011011100010000001010100011001010111001001100100011001010111010001100101011010110111001101101001 ,
b1110010011000010110101101100001011011100010000001010100011001010111001001100100011001010111010001100101011010110111001101101001 1
b100 !
b100 +
b100 3
b10000 (
b10000 .
b10000 ;
1*
b10 )
b10 /
b10 2
b10 9
1$
#42000
0$
#43000
b10001 (
b10001 .
b10001 ;
1$
#44000
0$
#45000
b10010 (
b10010 .
b10010 ;
1$
#46000
0$
#47000
b10011 (
b10011 .
b10011 ;
1$
#48000
0$
#49000
b10100 (
b10100 .
b10100 ;
1$
#50000
0$
0%
#51000
b10101 (
b10101 .
b10101 ;
1$
#52000
0$
#53000
b10110 (
b10110 .
b10110 ;
1$
#54000
0$
#55000
b10111 (
b10111 .
b10111 ;
1$
#56000
0$
#57000
b11000 (
b11000 .
b11000 ;
1$
#58000
0$
#59000
b11001 (
b11001 .
b11001 ;
1$
#60000
0$
#61000
b11010 (
b11010 .
b11010 ;
1$
#62000
0$
#63000
b11011 (
b11011 .
b11011 ;
1$
#64000
0$
#65000
b11100 (
b11100 .
b11100 ;
1$
#66000
0$
#67000
b11101 (
b11101 .
b11101 ;
1$
#68000
0$
#69000
b11110 (
b11110 .
b11110 ;
1$
#70000
0$
#71000
b11111 (
b11111 .
b11111 ;
1$
#72000
0$
#73000
b100000 (
b100000 .
b100000 ;
1$
#74000
0$
#75000
b100001 (
b100001 .
b100001 ;
1$
#76000
0$
#77000
b100010 (
b100010 .
b100010 ;
1$
#78000
0$
#79000
b100011 (
b100011 .
b100011 ;
1$
#80000
0$
1&
#81000
0#
b100001101101111011101010110111001110100011001000110111101110111011011100011101000100000000000 "
b100001101101111011101010110111001110100011001000110111101110111011011100011101000100000000000 ,
b100001101101111011101010110111001110100011001000110111101110111011011100011101000100000000000 1
b1 !
b1 +
b1 3
b100100 (
b100100 .
b100100 ;
b111100 8
0*
b11 )
b11 /
b11 2
b11 9
1$
#82000
0$
#83000
b111011 8
b100101 (
b100101 .
b100101 ;
1$
#84000
0$
#85000
b100110 (
b100110 .
b100110 ;
b111010 8
1$
#86000
0$
#87000
b111001 8
b100111 (
b100111 .
b100111 ;
1$
#88000
0$
#89000
b101000 (
b101000 .
b101000 ;
b111000 8
1$
#90000
0$
0&
#91000
b110111 8
b101001 (
b101001 .
b101001 ;
1$
#92000
0$
#93000
b101010 (
b101010 .
b101010 ;
b110110 8
1$
#94000
0$
#95000
b110101 8
b101011 (
b101011 .
b101011 ;
1$
#96000
0$
#97000
b101100 (
b101100 .
b101100 ;
b110100 8
1$
#98000
0$
#99000
b110011 8
b101101 (
b101101 .
b101101 ;
1$
#100000
0$
#101000
b101110 (
b101110 .
b101110 ;
b110010 8
1$
#102000
0$
#103000
b110001 8
b101111 (
b101111 .
b101111 ;
1$
#104000
0$
#105000
b110000 (
b110000 .
b110000 ;
b110000 8
1$
#106000
0$
#107000
b101111 8
b110001 (
b110001 .
b110001 ;
1$
#108000
0$
#109000
b110010 (
b110010 .
b110010 ;
b101110 8
1$
#110000
0$
#111000
b101101 8
b110011 (
b110011 .
b110011 ;
1$
#112000
0$
#113000
b110100 (
b110100 .
b110100 ;
b101100 8
1$
#114000
0$
#115000
b101011 8
b110101 (
b110101 .
b110101 ;
1$
#116000
0$
#117000
b110110 (
b110110 .
b110110 ;
b101010 8
1$
#118000
0$
#119000
b101001 8
b110111 (
b110111 .
b110111 ;
1$
#120000
0$
#121000
b111000 (
b111000 .
b111000 ;
b101000 8
1$
#122000
0$
#123000
b100111 8
b111001 (
b111001 .
b111001 ;
1$
#124000
0$
#125000
b111010 (
b111010 .
b111010 ;
b100110 8
1$
#126000
0$
#127000
b100101 8
b111011 (
b111011 .
b111011 ;
1$
#128000
0$
#129000
b111100 (
b111100 .
b111100 ;
b100100 8
1$
#130000
0$
#131000
b100011 8
b111101 (
b111101 .
b111101 ;
1$
#132000
0$
#133000
b111110 (
b111110 .
b111110 ;
b100010 8
1$
#134000
0$
#135000
b100001 8
b111111 (
b111111 .
b111111 ;
1$
#136000
0$
#137000
b1000000 (
b1000000 .
b1000000 ;
b100000 8
1$
#138000
0$
#139000
b11111 8
b1000001 (
b1000001 .
b1000001 ;
1$
#140000
0$
#141000
b1000010 (
b1000010 .
b1000010 ;
b11110 8
1$
#142000
0$
#143000
b11101 8
b1000011 (
b1000011 .
b1000011 ;
1$
#144000
0$
#145000
b1000100 (
b1000100 .
b1000100 ;
b11100 8
1$
#146000
0$
#147000
b11011 8
b1000101 (
b1000101 .
b1000101 ;
1$
#148000
0$
#149000
b1000110 (
b1000110 .
b1000110 ;
b11010 8
1$
#150000
0$
#151000
b11001 8
b1000111 (
b1000111 .
b1000111 ;
1$
#152000
0$
#153000
b1001000 (
b1001000 .
b1001000 ;
b11000 8
1$
#154000
0$
#155000
b10111 8
b1001001 (
b1001001 .
b1001001 ;
1$
#156000
0$
#157000
b1001010 (
b1001010 .
b1001010 ;
b10110 8
1$
#158000
0$
#159000
b10101 8
b1001011 (
b1001011 .
b1001011 ;
1$
#160000
0$
#161000
b1001100 (
b1001100 .
b1001100 ;
b10100 8
1$
#162000
0$
#163000
b10011 8
b1001101 (
b1001101 .
b1001101 ;
1$
#164000
0$
#165000
b1001110 (
b1001110 .
b1001110 ;
b10010 8
1$
#166000
0$
#167000
b10001 8
b1001111 (
b1001111 .
b1001111 ;
1$
#168000
0$
#169000
b1010000 (
b1010000 .
b1010000 ;
b10000 8
1$
#170000
0$
#171000
b1111 8
b1010001 (
b1010001 .
b1010001 ;
1$
#172000
0$
#173000
b1010010 (
b1010010 .
b1010010 ;
b1110 8
1$
#174000
0$
#175000
b1101 8
b1010011 (
b1010011 .
b1010011 ;
1$
#176000
0$
#177000
b1010100 (
b1010100 .
b1010100 ;
b1100 8
1$
#178000
0$
#179000
b1011 8
b1010101 (
b1010101 .
b1010101 ;
1$
#180000
0$
#181000
b1010110 (
b1010110 .
b1010110 ;
b1010 8
1$
#182000
0$
#183000
b1001 8
b1010111 (
b1010111 .
b1010111 ;
1$
#184000
0$
#185000
b1011000 (
b1011000 .
b1011000 ;
b1000 8
1$
#186000
0$
#187000
b111 8
b1011001 (
b1011001 .
b1011001 ;
1$
#188000
0$
#189000
b1011010 (
b1011010 .
b1011010 ;
b110 8
1$
#190000
0$
#191000
b101 8
b1011011 (
b1011011 .
b1011011 ;
1$
#192000
0$
#193000
b1011100 (
b1011100 .
b1011100 ;
b100 8
1$
#194000
0$
#195000
b11 8
b1011101 (
b1011101 .
b1011101 ;
1$
#196000
0$
#197000
b1011110 (
b1011110 .
b1011110 ;
b10 8
1$
#198000
0$
#199000
b1 8
b1011111 (
b1011111 .
b1011111 ;
1$
#200000
0$
#201000
b1100000 (
b1100000 .
b1100000 ;
b0 8
1$
#202000
0$
#203000
b10 !
b10 +
b10 3
b1101110011100110110111101110010001000000110000101101011011101000110100101100110001110100010000000000000000000000000000001100001 "
b1101110011100110110111101110010001000000110000101101011011101000110100101100110001110100010000000000000000000000000000001100001 ,
b1101110011100110110111101110010001000000110000101101011011101000110100101100110001110100010000000000000000000000000000001100001 1
b1 )
b1 /
b1 2
b1 9
b1100001 (
b1100001 .
b1100001 ;
1$
#204000
0$
#205000
b1101110011100110110111101110010001000000110000101101011011101000110100101100110001110100010000000000000000000000000000001100010 "
b1101110011100110110111101110010001000000110000101101011011101000110100101100110001110100010000000000000000000000000000001100010 ,
b1101110011100110110111101110010001000000110000101101011011101000110100101100110001110100010000000000000000000000000000001100010 1
b1100010 (
b1100010 .
b1100010 ;
1$
#206000
0$
#207000
b1101110011100110110111101110010001000000110000101101011011101000110100101100110001110100010000000000000000000000000000001100011 "
b1101110011100110110111101110010001000000110000101101011011101000110100101100110001110100010000000000000000000000000000001100011 ,
b1101110011100110110111101110010001000000110000101101011011101000110100101100110001110100010000000000000000000000000000001100011 1
b1100011 (
b1100011 .
b1100011 ;
1$
#208000
0$
#209000
b1101110011100110110111101110010001000000110000101101011011101000110100101100110001110100010000000000000000000000000000001100100 "
b1101110011100110110111101110010001000000110000101101011011101000110100101100110001110100010000000000000000000000000000001100100 ,
b1101110011100110110111101110010001000000110000101101011011101000110100101100110001110100010000000000000000000000000000001100100 1
b1100100 (
b1100100 .
b1100100 ;
1$
#210000
0$
#211000
b1101110011100110110111101110010001000000110000101101011011101000110100101100110001110100010000000000000000000000000000001100101 "
b1101110011100110110111101110010001000000110000101101011011101000110100101100110001110100010000000000000000000000000000001100101 ,
b1101110011100110110111101110010001000000110000101101011011101000110100101100110001110100010000000000000000000000000000001100101 1
b1100101 (
b1100101 .
b1100101 ;
1$
#212000
0$
#213000
b1101110011100110110111101110010001000000110000101101011011101000110100101100110001110100010000000000000000000000000000001100110 "
b1101110011100110110111101110010001000000110000101101011011101000110100101100110001110100010000000000000000000000000000001100110 ,
b1101110011100110110111101110010001000000110000101101011011101000110100101100110001110100010000000000000000000000000000001100110 1
b1100110 (
b1100110 .
b1100110 ;
1$
#214000
0$
#215000
b1101110011100110110111101110010001000000110000101101011011101000110100101100110001110100010000000000000000000000000000001100111 "
b1101110011100110110111101110010001000000110000101101011011101000110100101100110001110100010000000000000000000000000000001100111 ,
b1101110011100110110111101110010001000000110000101101011011101000110100101100110001110100010000000000000000000000000000001100111 1
b1100111 (
b1100111 .
b1100111 ;
1$
#216000
0$
#217000
b1101110011100110110111101110010001000000110000101101011011101000110100101100110001110100010000000000000000000000000000001101000 "
b1101110011100110110111101110010001000000110000101101011011101000110100101100110001110100010000000000000000000000000000001101000 ,
b1101110011100110110111101110010001000000110000101101011011101000110100101100110001110100010000000000000000000000000000001101000 1
b1101000 (
b1101000 .
b1101000 ;
1$
#218000
0$
#219000
b1101110011100110110111101110010001000000110000101101011011101000110100101100110001110100010000000000000000000000000000001101001 "
b1101110011100110110111101110010001000000110000101101011011101000110100101100110001110100010000000000000000000000000000001101001 ,
b1101110011100110110111101110010001000000110000101101011011101000110100101100110001110100010000000000000000000000000000001101001 1
b1101001 (
b1101001 .
b1101001 ;
1$
#220000
0$
#221000
b1101110011100110110111101110010001000000110000101101011011101000110100101100110001110100010000000000000000000000000000001101010 "
b1101110011100110110111101110010001000000110000101101011011101000110100101100110001110100010000000000000000000000000000001101010 ,
b1101110011100110110111101110010001000000110000101101011011101000110100101100110001110100010000000000000000000000000000001101010 1
b1101010 (
b1101010 .
b1101010 ;
1$
#222000
0$
#223000
b1101110011100110110111101110010001000000110000101101011011101000110100101100110001110100010000000000000000000000000000001101011 "
b1101110011100110110111101110010001000000110000101101011011101000110100101100110001110100010000000000000000000000000000001101011 ,
b1101110011100110110111101110010001000000110000101101011011101000110100101100110001110100010000000000000000000000000000001101011 1
b1101011 (
b1101011 .
b1101011 ;
1$
#224000
0$
#225000
b1101110011100110110111101110010001000000110000101101011011101000110100101100110001110100010000000000000000000000000000001101100 "
b1101110011100110110111101110010001000000110000101101011011101000110100101100110001110100010000000000000000000000000000001101100 ,
b1101110011100110110111101110010001000000110000101101011011101000110100101100110001110100010000000000000000000000000000001101100 1
b1101100 (
b1101100 .
b1101100 ;
1$
#226000
0$
#227000
b1101110011100110110111101110010001000000110000101101011011101000110100101100110001110100010000000000000000000000000000001101101 "
b1101110011100110110111101110010001000000110000101101011011101000110100101100110001110100010000000000000000000000000000001101101 ,
b1101110011100110110111101110010001000000110000101101011011101000110100101100110001110100010000000000000000000000000000001101101 1
b1101101 (
b1101101 .
b1101101 ;
1$
#228000
0$
#229000
b1101110011100110110111101110010001000000110000101101011011101000110100101100110001110100010000000000000000000000000000001101110 "
b1101110011100110110111101110010001000000110000101101011011101000110100101100110001110100010000000000000000000000000000001101110 ,
b1101110011100110110111101110010001000000110000101101011011101000110100101100110001110100010000000000000000000000000000001101110 1
b1101110 (
b1101110 .
b1101110 ;
1$
#230000
0$
#231000
b1101110011100110110111101110010001000000110000101101011011101000110100101100110001110100010000000000000000000000000000001101111 "
b1101110011100110110111101110010001000000110000101101011011101000110100101100110001110100010000000000000000000000000000001101111 ,
b1101110011100110110111101110010001000000110000101101011011101000110100101100110001110100010000000000000000000000000000001101111 1
b1101111 (
b1101111 .
b1101111 ;
1$
#232000
0$
#233000
b1101110011100110110111101110010001000000110000101101011011101000110100101100110001110100010000000000000000000000000000001110000 "
b1101110011100110110111101110010001000000110000101101011011101000110100101100110001110100010000000000000000000000000000001110000 ,
b1101110011100110110111101110010001000000110000101101011011101000110100101100110001110100010000000000000000000000000000001110000 1
b1110000 (
b1110000 .
b1110000 ;
1$
#234000
0$
#235000
b1101110011100110110111101110010001000000110000101101011011101000110100101100110001110100010000000000000000000000000000001110001 "
b1101110011100110110111101110010001000000110000101101011011101000110100101100110001110100010000000000000000000000000000001110001 ,
b1101110011100110110111101110010001000000110000101101011011101000110100101100110001110100010000000000000000000000000000001110001 1
b1110001 (
b1110001 .
b1110001 ;
1$
#236000
0$
#237000
b1101110011100110110111101110010001000000110000101101011011101000110100101100110001110100010000000000000000000000000000001110010 "
b1101110011100110110111101110010001000000110000101101011011101000110100101100110001110100010000000000000000000000000000001110010 ,
b1101110011100110110111101110010001000000110000101101011011101000110100101100110001110100010000000000000000000000000000001110010 1
b1110010 (
b1110010 .
b1110010 ;
1$
#238000
0$
#239000
b1101110011100110110111101110010001000000110000101101011011101000110100101100110001110100010000000000000000000000000000001110011 "
b1101110011100110110111101110010001000000110000101101011011101000110100101100110001110100010000000000000000000000000000001110011 ,
b1101110011100110110111101110010001000000110000101101011011101000110100101100110001110100010000000000000000000000000000001110011 1
b1110011 (
b1110011 .
b1110011 ;
1$
#240000
0$
#241000
b1101110011100110110111101110010001000000110000101101011011101000110100101100110001110100010000000000000000000000000000001110100 "
b1101110011100110110111101110010001000000110000101101011011101000110100101100110001110100010000000000000000000000000000001110100 ,
b1101110011100110110111101110010001000000110000101101011011101000110100101100110001110100010000000000000000000000000000001110100 1
b1110100 (
b1110100 .
b1110100 ;
1$
#242000
0$
#243000
b1101110011100110110111101110010001000000110000101101011011101000110100101100110001110100010000000000000000000000000000001110101 "
b1101110011100110110111101110010001000000110000101101011011101000110100101100110001110100010000000000000000000000000000001110101 ,
b1101110011100110110111101110010001000000110000101101011011101000110100101100110001110100010000000000000000000000000000001110101 1
b1110101 (
b1110101 .
b1110101 ;
1$
#244000
0$
#245000
b1101110011100110110111101110010001000000110000101101011011101000110100101100110001110100010000000000000000000000000000001110110 "
b1101110011100110110111101110010001000000110000101101011011101000110100101100110001110100010000000000000000000000000000001110110 ,
b1101110011100110110111101110010001000000110000101101011011101000110100101100110001110100010000000000000000000000000000001110110 1
b1110110 (
b1110110 .
b1110110 ;
1$
#246000
0$
#247000
b1101110011100110110111101110010001000000110000101101011011101000110100101100110001110100010000000000000000000000000000001110111 "
b1101110011100110110111101110010001000000110000101101011011101000110100101100110001110100010000000000000000000000000000001110111 ,
b1101110011100110110111101110010001000000110000101101011011101000110100101100110001110100010000000000000000000000000000001110111 1
b1110111 (
b1110111 .
b1110111 ;
1$
#248000
0$
#249000
b1101110011100110110111101110010001000000110000101101011011101000110100101100110001110100010000000000000000000000000000001111000 "
b1101110011100110110111101110010001000000110000101101011011101000110100101100110001110100010000000000000000000000000000001111000 ,
b1101110011100110110111101110010001000000110000101101011011101000110100101100110001110100010000000000000000000000000000001111000 1
b1111000 (
b1111000 .
b1111000 ;
1$
#250000
0$
#251000
b1101110011100110110111101110010001000000110000101101011011101000110100101100110001110100010000000000000000000000000000001111001 "
b1101110011100110110111101110010001000000110000101101011011101000110100101100110001110100010000000000000000000000000000001111001 ,
b1101110011100110110111101110010001000000110000101101011011101000110100101100110001110100010000000000000000000000000000001111001 1
b1111001 (
b1111001 .
b1111001 ;
1$
#252000
0$
#253000
b1101110011100110110111101110010001000000110000101101011011101000110100101100110001110100010000000000000000000000000000001111010 "
b1101110011100110110111101110010001000000110000101101011011101000110100101100110001110100010000000000000000000000000000001111010 ,
b1101110011100110110111101110010001000000110000101101011011101000110100101100110001110100010000000000000000000000000000001111010 1
b1111010 (
b1111010 .
b1111010 ;
1$
#254000
0$
#255000
b1101110011100110110111101110010001000000110000101101011011101000110100101100110001110100010000000000000000000000000000001111011 "
b1101110011100110110111101110010001000000110000101101011011101000110100101100110001110100010000000000000000000000000000001111011 ,
b1101110011100110110111101110010001000000110000101101011011101000110100101100110001110100010000000000000000000000000000001111011 1
b1111011 (
b1111011 .
b1111011 ;
1$
#256000
0$
#257000
b1101110011100110110111101110010001000000110000101101011011101000110100101100110001110100010000000000000000000000000000001111100 "
b1101110011100110110111101110010001000000110000101101011011101000110100101100110001110100010000000000000000000000000000001111100 ,
b1101110011100110110111101110010001000000110000101101011011101000110100101100110001110100010000000000000000000000000000001111100 1
b1111100 (
b1111100 .
b1111100 ;
1$
#258000
0$
#259000
b1101110011100110110111101110010001000000110000101101011011101000110100101100110001110100010000000000000000000000000000001111101 "
b1101110011100110110111101110010001000000110000101101011011101000110100101100110001110100010000000000000000000000000000001111101 ,
b1101110011100110110111101110010001000000110000101101011011101000110100101100110001110100010000000000000000000000000000001111101 1
b1111101 (
b1111101 .
b1111101 ;
1$
#260000
0$
